CHANGELOG
CONTRIBUTORS
ISSUES.txt
LICENSE
MANIFEST.in
README.md
setup.cfg
setup.py
tox.ini
doc/Makefile
doc/changelog.txt
doc/check_sphinx.py
doc/conf.py
doc/config-v2.txt
doc/config.txt
doc/examples.txt
doc/index.txt
doc/install.txt
doc/links.txt
doc/plugins.txt
doc/support.txt
doc/_static/sphinxdoc.css
doc/_templates/indexsidebar.html
doc/_templates/layout.html
doc/_templates/localtoc.html
doc/announce/release-0.5.txt
doc/announce/release-1.0.txt
doc/announce/release-1.1.txt
doc/announce/release-1.2.txt
doc/announce/release-1.3.txt
doc/announce/release-1.4.3.txt
doc/announce/release-1.4.txt
doc/announce/release-1.8.txt
doc/announce/release-1.9.txt
doc/announce/release-2.0.txt
doc/example/basic.txt
doc/example/devenv.txt
doc/example/general.txt
doc/example/jenkins.txt
doc/example/nose.txt
doc/example/pytest.txt
doc/example/result.txt
doc/example/unittest.txt
tests/conftest.py
tests/conftest.pyc
tests/test_config.py
tests/test_interpreters.py
tests/test_quickstart.py
tests/test_result.py
tests/test_venv.py
tests/test_z_cmdline.py
tests/__pycache__/conftest.cpython-34.pyc
tests/__pycache__/test_config.cpython-27-PYTEST.pyc
tests/__pycache__/test_config.cpython-34-PYTEST.pyc
tests/__pycache__/test_interpreters.cpython-27-PYTEST.pyc
tests/__pycache__/test_interpreters.cpython-34-PYTEST.pyc
tests/__pycache__/test_quickstart.cpython-27-PYTEST.pyc
tests/__pycache__/test_quickstart.cpython-34-PYTEST.pyc
tests/__pycache__/test_result.cpython-27-PYTEST.pyc
tests/__pycache__/test_result.cpython-34-PYTEST.pyc
tests/__pycache__/test_venv.cpython-27-PYTEST.pyc
tests/__pycache__/test_venv.cpython-34-PYTEST.pyc
tests/__pycache__/test_z_cmdline.cpython-27-PYTEST.pyc
tests/__pycache__/test_z_cmdline.cpython-34-PYTEST.pyc
tox_plus/__init__.py
tox_plus/__main__.py
tox_plus/_pytestplugin.py
tox_plus/_quickstart.py
tox_plus/_verlib.py
tox_plus/config.py
tox_plus/hookspecs.py
tox_plus/interpreters.py
tox_plus/result.py
tox_plus/session.py
tox_plus/venv.py
tox_plus.egg-info/PKG-INFO
tox_plus.egg-info/SOURCES.txt
tox_plus.egg-info/dependency_links.txt
tox_plus.egg-info/entry_points.txt
tox_plus.egg-info/pbr.json
tox_plus.egg-info/requires.txt
tox_plus.egg-info/top_level.txt