Metadata-Version: 1.1
Name: tox-plus
Version: 0.0.1
Summary: virtualenv-based automation of test activities
Home-page: https://github.com/Itxaka/tox-plus
Author: Itxaka serrano, Holger krekel
Author-email: itxakaserrano@gmail.com
License: http://opensource.org/licenses/MIT
Platform: unix
Platform: linux
Platform: osx
Platform: cygwin
Platform: win32
Classifier: Development Status :: 5 - Production/Stable
Classifier: Intended Audience :: Developers
Classifier: License :: OSI Approved :: MIT License
Classifier: Operating System :: POSIX
Classifier: Operating System :: Microsoft :: Windows
Classifier: Operating System :: MacOS :: MacOS X
Classifier: Topic :: Software Development :: Testing
Classifier: Topic :: Software Development :: Libraries
Classifier: Topic :: Utilities
Classifier: Programming Language :: Python
Classifier: Programming Language :: Python :: 3
